{"id":"state-assessors","name":"Assessor Management","title":"Assessor Management","layout":"dashboard","pageHeader":{"title":"Assessor Management","subtitle":"Create assessor profiles and map them to assigned units."},"authentication":{"required":true},"assets":{"css":["/ui/pages/state/dashboard.css?v=20260713-4","/ui/pages/state/assessors.css?v=20260718-1"],"js":["/ui/assets/js/core/pagination.js?v=20260713-1","/ui/pages/state/assessors.js?v=20260718-1"]},"breadcrumb":[{"label":"Dashboard","url":"/ui/dashboard.html"},{"label":"State Monitoring"},{"label":"Assessor Management"}],"moduleName":"stateAssessors"}
