{"id":"state-facility-category","name":"Facility Categorization","title":"Facility Categorization","layout":"dashboard","pageHeader":{"title":"Facility Categorization","subtitle":"State-wide facility distribution by type and geography."},"authentication":{"required":true},"assets":{"css":["/ui/pages/state/dashboard.css?v=20260713-1"],"js":["/ui/pages/state/facility-category.js?v=20260713-3"]},"breadcrumb":[{"label":"Dashboard","url":"/ui/dashboard.html"},{"label":"State Monitoring"},{"label":"Facility Categorization"}],"moduleName":"stateFacilityCategory"}
